rtapi/__init__.py
racktables_api-0.3.1.dist-info/LICENSE
racktables_api-0.3.1.dist-info/METADATA
racktables_api-0.3.1.dist-info/WHEEL
racktables_api-0.3.1.dist-info/top_level.txt
racktables_api-0.3.1.dist-info/RECORD
