Metadata-Version: 2.1
Name: racktables-api
Version: 0.3.1
Summary: Simple racktables API
Home-page: https://github.com/rvojcik/rtapi
Author: Robert Vojcik
Author-email: robert@vojcik.net
License: GPLv2
Keywords: rtapi,racktables,racktables api,racktables-api,racktables cli,racktables-cli
Platform: UNKNOWN
Classifier: License :: OSI Approved :: GNU General Public License v2 (GPLv2)
Classifier: Operating System :: POSIX
Classifier: Operating System :: Unix
Classifier: Programming Language :: Python
Classifier: Programming Language :: Python :: 3
Classifier: Programming Language :: Python :: 3.6
Classifier: Programming Language :: Python :: 3.7
Classifier: Programming Language :: Python :: 3.8
Classifier: Topic :: Database
Requires-Dist: ipaddress
